{
  "users": [
    {
      "id": "4",
      "name": "John Doe",
      "tasks": {
        "-Nn5uJ5OynHWxO66-3z8": {
          "description": "watch some good tutorial",
          "id": "-Nn5uJ5OynHWxO66-3z8",
          "title": "become great",
          "date_created": "2024-01-02"
        }
      }
    },
    {
      "id": "3",
      "name": "John Doe",
      "tasks": {
        "-Nn5uJ5OynHWxO66-3z8": {
          "description": "watch some good tutorial on how to fvk before wednesday",
          "id": "-Nn5uJ5OynHWxO66-3z8",
          "title": "Big me",
          "date_created": "2024-01-01"
        },
        "-Nn59syndUq_S-lmTEMc": {
          "description": "test description",
          "id": "-Nn59syndUq_S-lmTEMc",
          "title": "test",
          "date_created": "2024-01-02"
        }
      }
    }
  ]
}